debugsnacks/__init__.py
debugsnacks/chaos.py
debugsnacks/core.py
debugsnacks/excuses.py
debugsnacks/facts.py
debugsnacks/humor.py
debugsnacks/mood.py
debugsnacks/strings.py
debugsnacks-0.2.1.dist-info/licenses/LICENSE
debugsnacks-0.2.1.dist-info/METADATA
debugsnacks-0.2.1.dist-info/WHEEL
debugsnacks-0.2.1.dist-info/top_level.txt
debugsnacks-0.2.1.dist-info/RECORD
