Metadata-Version: 2.4
Name: debugsnacks
Version: 0.2.1
Summary: A playful Python utility library for fun, facts, and chaos.
Author: Mohammad Razi
License: MIT
Project-URL: Homepage, https://github.com/iammohdrazi/DebugSnacks
Project-URL: Repository, https://github.com/iammohdrazi/DebugSnacks
Project-URL: Issues, https://github.com/iammohdrazi/DebugSnacks/issues
Requires-Python: >=3.8
License-File: LICENSE
Dynamic: license-file
